bank_management_fc/__init__.py
bank_management_fc/account.py
bank_management_fc/balance.py
bank_management_fc/user.py
bank_management_fc-0.0.1.dist-info/METADATA
bank_management_fc-0.0.1.dist-info/WHEEL
bank_management_fc-0.0.1.dist-info/top_level.txt
bank_management_fc-0.0.1.dist-info/RECORD
