Metadata-Version: 2.4
Name: bank_management_fc
Version: 0.0.1
Summary: A bank management package
Home-page: https://github.com/FlowCreeper/dio-bank-management
Author: FlowCreeper
Author-email: caiocoutinho20120@gmail.com
Requires-Python: >=3.12.1
Dynamic: author
Dynamic: author-email
Dynamic: description
Dynamic: description-content-type
Dynamic: home-page
Dynamic: requires-python
Dynamic: summary
